bitrot.py
bitrot-1.0.1.dist-info/LICENSE
bitrot-1.0.1.dist-info/METADATA
bitrot-1.0.1.dist-info/WHEEL
bitrot-1.0.1.dist-info/entry_points.txt
bitrot-1.0.1.dist-info/top_level.txt
bitrot-1.0.1.dist-info/RECORD
