Metadata-Version: 2.1
Name: bitrot
Version: 1.0.1
Summary: Detects bit rotten files on the hard drive to save your precious photo and music collection from slow decay.
Author-email: Łukasz Langa <lukasz@langa.pl>
License: MIT
Keywords: file,checksum,database
Classifier: Development Status :: 5 - Production/Stable
Classifier: Natural Language :: English
Classifier: Programming Language :: Python :: 3
Classifier: Topic :: System :: Filesystems
Classifier: Topic :: System :: Monitoring
Classifier: Topic :: Software Development :: Libraries :: Python Modules
Requires-Python: >=3.8
License-File: LICENSE
Provides-Extra: test
Requires-Dist: pytest ; extra == 'test'
Requires-Dist: pytest-order ; extra == 'test'
